tftppilot/__init__.py
tftppilot/server.py
tftppilot/tftp.py
tftp_pilot-0.2.0.dist-info/LICENSE
tftp_pilot-0.2.0.dist-info/METADATA
tftp_pilot-0.2.0.dist-info/WHEEL
tftp_pilot-0.2.0.dist-info/top_level.txt
tftp_pilot-0.2.0.dist-info/RECORD
